vibectl/__init__.py
vibectl/cli.py
vibectl/command_handler.py
vibectl/config.py
vibectl/config_utils.py
vibectl/console.py
vibectl/k8s_utils.py
vibectl/live_display.py
vibectl/live_display_watch.py
vibectl/llm_interface.py
vibectl/llm_utils.py
vibectl/logutil.py
vibectl/memory.py
vibectl/model_adapter.py
vibectl/output_processor.py
vibectl/overrides.py
vibectl/plugins.py
vibectl/proxy.py
vibectl/proxy_model_adapter.py
vibectl/py.typed
vibectl/schema.py
vibectl/truncation_logic.py
vibectl/types.py
vibectl/utils.py
vibectl/version_compat.py
vibectl/execution/apply.py
vibectl/execution/check.py
vibectl/execution/edit.py
vibectl/execution/vibe.py
vibectl/prompts/__init__.py
vibectl/prompts/apply.py
vibectl/prompts/check.py
vibectl/prompts/cluster_info.py
vibectl/prompts/context.py
vibectl/prompts/create.py
vibectl/prompts/delete.py
vibectl/prompts/describe.py
vibectl/prompts/diff.py
vibectl/prompts/edit.py
vibectl/prompts/events.py
vibectl/prompts/get.py
vibectl/prompts/logs.py
vibectl/prompts/memory.py
vibectl/prompts/patch.py
vibectl/prompts/port_forward.py
vibectl/prompts/recovery.py
vibectl/prompts/rollout.py
vibectl/prompts/scale.py
vibectl/prompts/schemas.py
vibectl/prompts/shared.py
vibectl/prompts/version.py
vibectl/prompts/vibe.py
vibectl/prompts/wait.py
vibectl/proto/__init__.py
vibectl/proto/llm_proxy_pb2.py
vibectl/proto/llm_proxy_pb2_grpc.py
vibectl/security/__init__.py
vibectl/security/audit.py
vibectl/security/config.py
vibectl/security/response_validation.py
vibectl/security/sanitizer.py
vibectl/server/__init__.py
vibectl/server/acme_client.py
vibectl/server/acme_manager.py
vibectl/server/alpn_bridge.py
vibectl/server/alpn_multiplexer.py
vibectl/server/ca_manager.py
vibectl/server/cert_utils.py
vibectl/server/config.py
vibectl/server/grpc_server.py
vibectl/server/http_challenge_server.py
vibectl/server/jwt_auth.py
vibectl/server/jwt_interceptor.py
vibectl/server/limit_backend.py
vibectl/server/llm_proxy.py
vibectl/server/main.py
vibectl-0.11.6.dist-info/METADATA
vibectl-0.11.6.dist-info/WHEEL
vibectl-0.11.6.dist-info/entry_points.txt
vibectl-0.11.6.dist-info/licenses/LICENSE
vibectl-0.11.6.dist-info/RECORD
