Metadata-Version: 2.4
Name: vibectl
Version: 0.11.6
Summary: A vibes-based alternative to kubectl
Author-email: Daniel Klein <othercriteria@gmail.com>
License: MIT License
License-File: LICENSE
Classifier: Development Status :: 4 - Beta
Classifier: Intended Audience :: Developers
Classifier: Intended Audience :: System Administrators
Classifier: License :: OSI Approved :: MIT License
Classifier: Programming Language :: Python :: 3
Classifier: Programming Language :: Python :: 3.11
Classifier: Programming Language :: Python :: 3.12
Classifier: Topic :: System :: Systems Administration
Classifier: Topic :: Utilities
Requires-Python: >=3.11
Requires-Dist: acme<5.0.0,>=4.0.0
Requires-Dist: aiohttp<4.0.0,>=3.9.0
Requires-Dist: annotated-types<0.7.0,>=0.6.0
Requires-Dist: anyio<5.0.0,>=4.3.0
Requires-Dist: asyncclick>=8.0.1.2
Requires-Dist: click<9.0.0,>=8.1.7
Requires-Dist: cryptography>=41.0.0
Requires-Dist: distro<2.0.0,>=1.9.0
Requires-Dist: grpcio-tools<2.0.0,>=1.60.0
Requires-Dist: grpcio<2.0.0,>=1.60.0
Requires-Dist: httpx<0.28.0,>=0.27.0
Requires-Dist: josepy<3.0.0,>=2.0.0
Requires-Dist: kubernetes<30.0.0,>=29.0.0
Requires-Dist: llm>=0.13.0
Requires-Dist: prometheus-client<1.0.0,>=0.18.0
Requires-Dist: pyjwt<3.0.0,>=2.8.0
Requires-Dist: pyyaml>=6.0.0
Requires-Dist: requests>=2.31.0
Requires-Dist: rich>=13.0.0
Provides-Extra: dev
Requires-Dist: asyncmock>=0.4.2; extra == 'dev'
Requires-Dist: build>=1.2.1; extra == 'dev'
Requires-Dist: grpc-stubs>=1.53.0; extra == 'dev'
Requires-Dist: mypy>=1.5.0; extra == 'dev'
Requires-Dist: pre-commit>=3.7.0; extra == 'dev'
Requires-Dist: pydantic>=2.0.0; extra == 'dev'
Requires-Dist: pytest-asyncio<0.27,>=0.26.0; extra == 'dev'
Requires-Dist: pytest-cov>=4.1.0; extra == 'dev'
Requires-Dist: pytest-mock>=3.12.0; extra == 'dev'
Requires-Dist: pytest-timeout>=2.3.0; extra == 'dev'
Requires-Dist: pytest-xdist>=3.5.0; extra == 'dev'
Requires-Dist: pytest>=7.0.0; extra == 'dev'
Requires-Dist: ruff>=0.3.0; extra == 'dev'
Requires-Dist: types-docker>=6.1.3; extra == 'dev'
Requires-Dist: types-flask-socketio>=5.0.0; extra == 'dev'
Requires-Dist: types-protobuf>=4.24.0; extra == 'dev'
Requires-Dist: types-pyyaml>=6.0.0; extra == 'dev'
Requires-Dist: types-requests>=2.31.0; extra == 'dev'
Requires-Dist: uv>=0.1.0; extra == 'dev'
Requires-Dist: virtualenv>=20.25.0; extra == 'dev'
